virusrecom/__init__.py
virusrecom/corecp.py
virusrecom/main.py
virusrecom/my_func.py
virusrecom/plt_corlor_list.py
virusrecom/sequence_align.py
virusrecom/wic_engine.py
virusrecom-1.3.7.dist-info/LICENSE
virusrecom-1.3.7.dist-info/METADATA
virusrecom-1.3.7.dist-info/WHEEL
virusrecom-1.3.7.dist-info/entry_points.txt
virusrecom-1.3.7.dist-info/top_level.txt
virusrecom-1.3.7.dist-info/RECORD
