Metadata-Version: 2.1
Name: virusrecom
Version: 1.3.7
Summary: An information-theory-based method for recombination detection of viral lineages.
Home-page: https://github.com/ZhijianZhou01/virusrecom
Author: Zhi-Jian Zhou
Author-email: zjzhou@hnu.edu.cn
Keywords: recombination,virus,evolution,information entropy
Classifier: Development Status :: 5 - Production/Stable
Classifier: Environment :: Console
Classifier: Intended Audience :: Developers
Classifier: Intended Audience :: Science/Research
Classifier: Topic :: Scientific/Engineering
Classifier: Topic :: Scientific/Engineering :: Bio-Informatics
Classifier: Topic :: Scientific/Engineering :: Visualization
Classifier: Topic :: Scientific/Engineering :: Mathematics
Classifier: Programming Language :: Python :: 3.5
Classifier: Programming Language :: Python :: 3.6
Classifier: Programming Language :: Python :: 3.7
Classifier: Programming Language :: Python :: 3.8
Classifier: Programming Language :: Python :: 3.9
Classifier: Programming Language :: Python :: 3.10
Classifier: Programming Language :: Python :: 3.11
Classifier: License :: OSI Approved :: GNU Lesser General Public License v2 or later (LGPLv2+)
Classifier: Operating System :: OS Independent
License-File: LICENSE
Requires-Dist: matplotlib >=2.2.5
Requires-Dist: numpy >=1.19.3
Requires-Dist: pandas >=1.1.5
Requires-Dist: scipy >=1.5.4
Requires-Dist: psutil >=5.9.1
Requires-Dist: openpyxl >=3.0.5
